{
  "color-primary-100": "#FEFBE3",
  "color-primary-200": "#FEF6C7",
  "color-primary-300": "#FCEEAB",
  "color-primary-400": "#F9E695",
  "color-primary-500": "#F6DA73",
  "color-primary-600": "#D3B554",
  "color-primary-700": "#B19239",
  "color-primary-800": "#8E7024",
  "color-primary-900": "#765916",
  "color-primary-transparent-100": "rgba(246, 218, 115, 0.08)",
  "color-primary-transparent-200": "rgba(246, 218, 115, 0.16)",
  "color-primary-transparent-300": "rgba(246, 218, 115, 0.24)",
  "color-primary-transparent-400": "rgba(246, 218, 115, 0.32)",
  "color-primary-transparent-500": "rgba(246, 218, 115, 0.4)",
  "color-primary-transparent-600": "rgba(246, 218, 115, 0.48)",
  "color-success-100": "#F0FDD8",
  "color-success-200": "#DDFBB1",
  "color-success-300": "#C3F388",
  "color-success-400": "#A7E768",
  "color-success-500": "#7FD83A",
  "color-success-600": "#61B92A",
  "color-success-700": "#469B1D",
  "color-success-800": "#2F7D12",
  "color-success-900": "#1E670B",
  "color-success-transparent-100": "rgba(127, 216, 58, 0.08)",
  "color-success-transparent-200": "rgba(127, 216, 58, 0.16)",
  "color-success-transparent-300": "rgba(127, 216, 58, 0.24)",
  "color-success-transparent-400": "rgba(127, 216, 58, 0.32)",
  "color-success-transparent-500": "rgba(127, 216, 58, 0.4)",
  "color-success-transparent-600": "rgba(127, 216, 58, 0.48)",
  "color-info-100": "#EEF6E5",
  "color-info-200": "#DCEDCC",
  "color-info-300": "#B2CBA0",
  "color-info-400": "#7D9770",
  "color-info-500": "#3e5336",
  "color-info-600": "#2E4727",
  "color-info-700": "#1F3B1B",
  "color-info-800": "#133011",
  "color-info-900": "#0A270A",
  "color-info-transparent-100": "rgba(62, 83, 54, 0.08)",
  "color-info-transparent-200": "rgba(62, 83, 54, 0.16)",
  "color-info-transparent-300": "rgba(62, 83, 54, 0.24)",
  "color-info-transparent-400": "rgba(62, 83, 54, 0.32)",
  "color-info-transparent-500": "rgba(62, 83, 54, 0.4)",
  "color-info-transparent-600": "rgba(62, 83, 54, 0.48)",
  "color-warning-100": "#FFF8D9",
  "color-warning-200": "#FFEFB3",
  "color-warning-300": "#FFE38D",
  "color-warning-400": "#FFD871",
  "color-warning-500": "#FFC642",
  "color-warning-600": "#DBA230",
  "color-warning-700": "#B78021",
  "color-warning-800": "#936115",
  "color-warning-900": "#7A4B0C",
  "color-warning-transparent-100": "rgba(255, 198, 66, 0.08)",
  "color-warning-transparent-200": "rgba(255, 198, 66, 0.16)",
  "color-warning-transparent-300": "rgba(255, 198, 66, 0.24)",
  "color-warning-transparent-400": "rgba(255, 198, 66, 0.32)",
  "color-warning-transparent-500": "rgba(255, 198, 66, 0.4)",
  "color-warning-transparent-600": "rgba(255, 198, 66, 0.48)",
  "color-danger-100": "#FDE3DF",
  "color-danger-200": "#FCC1BF",
  "color-danger-300": "#F79DA3",
  "color-danger-400": "#EF8394",
  "color-danger-500": "#e55b7e",
  "color-danger-600": "#C44270",
  "color-danger-700": "#A42D63",
  "color-danger-800": "#841D55",
  "color-danger-900": "#6D114C",
  "color-danger-transparent-100": "rgba(229, 91, 126, 0.08)",
  "color-danger-transparent-200": "rgba(229, 91, 126, 0.16)",
  "color-danger-transparent-300": "rgba(229, 91, 126, 0.24)",
  "color-danger-transparent-400": "rgba(229, 91, 126, 0.32)",
  "color-danger-transparent-500": "rgba(229, 91, 126, 0.4)",
  "color-danger-transparent-600": "rgba(229, 91, 126, 0.48)"
}